[{"Year":2001,"Value":0.4897},{"Year":2002,"Value":0.4635},{"Year":2003,"Value":0.5291},{"Year":2004,"Value":0.5835},{"Year":2005,"Value":0.6387},{"Year":2006,"Value":0.5888},{"Year":2007,"Value":0.6378},{"Year":2008,"Value":0.4243},{"Year":2009,"Value":0.4053},{"Year":2010,"Value":0.3584},{"Year":2011,"Value":0.3621},{"Year":2012,"Value":0.3715},{"Year":2013,"Value":0.3725},{"Year":2014,"Value":0.3769},{"Year":2015,"Value":0.368},{"Year":2016,"Value":0.3747},{"Year":2017,"Value":0.485},{"Year":2018,"Value":0.4452},{"Year":2019,"Value":0.3994}]