{"3-8-2":[{"Year":2015,"Value":2},{"Year":2016,"Value":2}],"10-7-1":[{"Year":2000,"Value":7.967725668},{"Year":2006,"Value":6.785270997},{"Year":2012,"Value":7.237687366},{"Year":2018,"Value":6.845238095}],"8-2-1":[{"Year":2006,"Value":0.004858824},{"Year":2007,"Value":0.044280828},{"Year":2008,"Value":0.019336521},{"Year":2009,"Value":0.016910647},{"Year":2010,"Value":-0.018196053},{"Year":2011,"Value":0.010588952},{"Year":2012,"Value":-0.004547809},{"Year":2013,"Value":0.016646885},{"Year":2014,"Value":-0.002589976},{"Year":2015,"Value":0.016620031},{"Year":2016,"Value":0.018045264},{"Year":2017,"Value":-0.001645704},{"Year":2018,"Value":0.017512831}],"8-b-1":[{"Year":2015,"Value":2},{"Year":2016,"Value":2}],"11-4-1":[{"Year":2015,"Value":2},{"Year":2016,"Value":2}],"7-1-1":[{"Year":1990,"Value":100.0},{"Year":1991,"Value":100.0},{"Year":1992,"Value":100.0},{"Year":1993,"Value":100.0},{"Year":1994,"Value":100.0},{"Year":1995,"Value":100.0},{"Year":1996,"Value":100.0},{"Year":1997,"Value":100.0},{"Year":1998,"Value":100.0},{"Year":1999,"Value":100.0},{"Year":2000,"Value":100.0},{"Year":2001,"Value":100.0},{"Year":2002,"Value":100.0},{"Year":2003,"Value":100.0},{"Year":2004,"Value":100.0},{"Year":2005,"Value":100.0},{"Year":2006,"Value":100.0},{"Year":2007,"Value":100.0},{"Year":2008,"Value":100.0},{"Year":2009,"Value":100.0},{"Year":2010,"Value":100.0},{"Year":2011,"Value":100.0},{"Year":2012,"Value":100.0},{"Year":2013,"Value":100.0},{"Year":2014,"Value":100.0},{"Year":2015,"Value":100.0},{"Year":2016,"Value":100.0},{"Year":2017,"Value":100.0}],"3-3-2":[{"Year":2010,"Value":6.6},{"Year":2011,"Value":2.82},{"Year":2012,"Value":3.43},{"Year":2013,"Value":3.71},{"Year":2014,"Value":2.75},{"Year":2015,"Value":2.42},{"Year":2016,"Value":1.79},{"Year":2017,"Value":2.9},{"Year":2018,"Value":0.9}],"15-a-1":[{"Year":2015,"Value":2},{"Year":2016,"Value":2}],"5-5-2":[],"3-d-1":[{"Year":2015,"Value":2},{"Year":2016,"Value":2}],"11-5-1":[{"Year":2015,"Value":2},{"Year":2016,"Value":2}],"12-2-1":[{"Year":2015,"Value":2},{"Year":2016,"Value":2}],"9-c-1":[{"Year":2015,"Value":2},{"Year":2016,"Value":2}],"3-4-2":[{"Year":2000,"Value":17.91800006},{"Year":2001,"Value":12.70464178},{"Year":2002,"Value":9.770566169},{"Year":2003,"Value":9.013037706},{"Year":2004,"Value":12.04529029},{"Year":2005,"Value":11.24066259},{"Year":2006,"Value":10.67054363},{"Year":2007,"Value":12.0257937},{"Year":2008,"Value":12.04593941},{"Year":2009,"Value":11.27226272},{"Year":2010,"Value":14.48225923},{"Year":2011,"Value":8.478514815},{"Year":2012,"Value":11.57787687},{"Year":2013,"Value":15.22415234},{"Year":2014,"Value":13.51056741},{"Year":2015,"Value":12.45821939},{"Year":2016,"Value":12.02902604},{"Year":2017,"Value":10.04879577}],"10-6-1":[{"Year":2015,"Value":2},{"Year":2016,"Value":2}],"3-4-1":[{"Year":2000,"Value":468},{"Year":2001,"Value":446},{"Year":2002,"Value":471},{"Year":2003,"Value":462},{"Year":2004,"Value":463},{"Year":2005,"Value":433},{"Year":2006,"Value":439},{"Year":2007,"Value":448},{"Year":2008,"Value":436},{"Year":2009,"Value":451},{"Year":2010,"Value":450},{"Year":2011,"Value":438},{"Year":2012,"Value":421},{"Year":2013,"Value":444},{"Year":2014,"Value":429},{"Year":2015,"Value":443},{"Year":2016,"Value":463},{"Year":2017,"Value":422}],"17-6-2":[{"Year":2015,"Value":2},{"Year":2016,"Value":2}],"16-6-1":[{"Year":2015,"Value":2},{"Year":2016,"Value":2}],"4-5-1":[{"Year":2015,"Value":2},{"Year":2016,"Value":2}],"17-2-1":[{"Year":2015,"Value":2},{"Year":2016,"Value":2}],"5-4-1":[{"Year":2015,"Value":2},{"Year":2016,"Value":2}],"16-3-1":[{"Year":2008,"Value":38.5},{"Year":2009,"Value":42.2},{"Year":2011,"Value":45.8},{"Year":2013,"Value":34.9},{"Year":2014,"Value":34.7},{"Year":2015,"Value":34.2},{"Year":2016,"Value":38.7},{"Year":2017,"Value":35.1},{"Year":2018,"Value":36.5}],"13-1-1":[{"Year":2015,"Value":2},{"Year":2016,"Value":2}],"15-8-1":[{"Year":2015,"Value":2},{"Year":2016,"Value":2}],"15-b-1":[{"Year":2015,"Value":2},{"Year":2016,"Value":2}],"6-4-2":[{"Year":2000,"Value":0.097058824},{"Year":2001,"Value":0.097058824},{"Year":2002,"Value":0.097058824},{"Year":2003,"Value":0.097058824},{"Year":2004,"Value":0.097058824},{"Year":2005,"Value":0.097058824},{"Year":2006,"Value":0.097058824},{"Year":2007,"Value":0.097058824},{"Year":2008,"Value":0.097058824},{"Year":2009,"Value":0.097058824},{"Year":2010,"Value":0.097058824},{"Year":2011,"Value":0.097058824},{"Year":2012,"Value":0.210058824},{"Year":2013,"Value":0.210058824},{"Year":2014,"Value":0.210058824},{"Year":2015,"Value":0.182352941},{"Year":2016,"Value":0.152941176},{"Year":2017,"Value":0.152941176}],"11-1-1":[],"10-b-1":[{"Year":2015,"Value":2},{"Year":2016,"Value":2}],"5-a-2":[{"Year":2015,"Value":2},{"Year":2016,"Value":2}],"10-4-1":[{"Year":2015,"Value":2},{"Year":2016,"Value":2}],"14-b-1":[{"Year":2015,"Value":2},{"Year":2016,"Value":2}],"3-3-5":[{"Year":2015,"Value":2},{"Year":2016,"Value":2}],"5-6-1":[{"Year":2015,"Value":2},{"Year":2016,"Value":2}],"3-9-1":[{"Year":2014,"Value":80},{"Year":2015,"Value":60}],"4-a-1":[{"Year":2015,"Value":2},{"Year":2016,"Value":2}],"1-a-1":[{"Year":2015,"Value":2},{"Year":2016,"Value":2}],"17-18-2":[{"Year":2015,"Value":2},{"Year":2016,"Value":2}],"2-5-1":[{"Year":2015,"Value":2},{"Year":2016,"Value":2}],"8-4-2":[{"Year":2015,"Value":2},{"Year":2016,"Value":2}],"16-4-1":[{"Year":2015,"Value":2},{"Year":2016,"Value":2}],"1-4-2":[{"Year":2015,"Value":2},{"Year":2016,"Value":2}],"1-b-1":[{"Year":2015,"Value":2},{"Year":2016,"Value":2}],"2-c-1":[{"Year":2016,"Value":-0.2},{"Year":2017,"Value":-0.9}],"8-7-1":[{"Year":2015,"Value":2},{"Year":2016,"Value":2}],"16-9-1":[{"Year":2015,"Value":2},{"Year":2016,"Value":2}],"4-c-1":[],"7-1-2":[{"Year":1990,"Value":100.0},{"Year":1991,"Value":100.0},{"Year":1992,"Value":100.0},{"Year":1993,"Value":100.0},{"Year":1994,"Value":100.0},{"Year":1995,"Value":100.0},{"Year":1996,"Value":100.0},{"Year":1997,"Value":100.0},{"Year":1998,"Value":100.0},{"Year":1999,"Value":100.0},{"Year":2000,"Value":100.0},{"Year":2001,"Value":100.0},{"Year":2002,"Value":100.0},{"Year":2003,"Value":100.0},{"Year":2004,"Value":100.0},{"Year":2005,"Value":100.0},{"Year":2006,"Value":100.0},{"Year":2007,"Value":100.0},{"Year":2008,"Value":100.0},{"Year":2009,"Value":100.0},{"Year":2010,"Value":100.0},{"Year":2011,"Value":100.0},{"Year":2012,"Value":100.0},{"Year":2013,"Value":100.0},{"Year":2014,"Value":100.0},{"Year":2015,"Value":100.0},{"Year":2016,"Value":100.0},{"Year":2017,"Value":100.0}],"12-6-1":[{"Year":2015,"Value":2},{"Year":2016,"Value":2}],"7-2-1":[{"Year":2004,"Value":58.8},{"Year":2005,"Value":60.0},{"Year":2006,"Value":60.7},{"Year":2007,"Value":71.4},{"Year":2008,"Value":67.3},{"Year":2009,"Value":69.6},{"Year":2010,"Value":70.3},{"Year":2011,"Value":71.5},{"Year":2012,"Value":72.4},{"Year":2013,"Value":71.7},{"Year":2014,"Value":70.5},{"Year":2015,"Value":70.3},{"Year":2016,"Value":72.7},{"Year":2017,"Value":71.6}],"1-1-1":[{"Year":2003,"Value":0.0},{"Year":2004,"Value":0.2},{"Year":2005,"Value":0.0},{"Year":2006,"Value":0.2},{"Year":2007,"Value":0.0},{"Year":2008,"Value":0.0},{"Year":2009,"Value":0.0},{"Year":2010,"Value":0.2},{"Year":2011,"Value":0.2},{"Year":2012,"Value":0.0},{"Year":2013,"Value":0.0},{"Year":2014,"Value":0.0}],"14-3-1":[{"Year":2015,"Value":2},{"Year":2016,"Value":2}],"11-b-1":[{"Year":2015,"Value":2},{"Year":2016,"Value":2}],"2-a-2":[{"Year":2015,"Value":2},{"Year":2016,"Value":2}],"15-1-2":[{"Year":2015,"Value":2},{"Year":2016,"Value":2}],"11-6-2":[],"2-5-2":[{"Year":2015,"Value":2},{"Year":2016,"Value":2}],"4-b-1":[{"Year":2016,"Value":582.7},{"Year":2017,"Value":673.0}],"9-b-1":[{"Year":2000,"Value":16.63},{"Year":2001,"Value":15.44},{"Year":2002,"Value":16.68},{"Year":2003,"Value":18.46},{"Year":2004,"Value":20.68},{"Year":2005,"Value":18.95},{"Year":2006,"Value":16.57},{"Year":2007,"Value":16.57},{"Year":2008,"Value":16.57},{"Year":2009,"Value":16.57},{"Year":2010,"Value":16.57},{"Year":2011,"Value":14.51},{"Year":2012,"Value":14.51},{"Year":2013,"Value":14.51},{"Year":2014,"Value":14.51},{"Year":2015,"Value":15.05},{"Year":2016,"Value":13.05}],"13-2-1":[{"Year":2015,"Value":2},{"Year":2016,"Value":2}],"9-3-1":[{"Year":2016,"Value":21.23},{"Year":2017,"Value":21.33}],"11-3-1":[{"Year":2006,"Value":2.747},{"Year":2012,"Value":-0.543},{"Year":2018,"Value":0.084}],"4-7-1":[{"Year":2015,"Value":2},{"Year":2016,"Value":2}],"15-1-1":[],"13-3-2":[{"Year":2015,"Value":2},{"Year":2016,"Value":2}],"14-a-1":[{"Year":2015,"Value":2},{"Year":2016,"Value":2}],"17-3-2":[{"Year":2015,"Value":2},{"Year":2016,"Value":2}],"11-a-1":[{"Year":2015,"Value":2},{"Year":2016,"Value":2}],"17-14-1":[{"Year":2015,"Value":2},{"Year":2016,"Value":2}],"3-6-1":[{"Year":1981,"Value":10},{"Year":1982,"Value":10},{"Year":1983,"Value":8},{"Year":1984,"Value":11},{"Year":1985,"Value":10},{"Year":1986,"Value":10},{"Year":1987,"Value":10},{"Year":1988,"Value":12},{"Year":1989,"Value":11},{"Year":1990,"Value":9},{"Year":1991,"Value":11},{"Year":1992,"Value":8},{"Year":1993,"Value":6},{"Year":1994,"Value":5},{"Year":1995,"Value":9},{"Year":1996,"Value":4},{"Year":1997,"Value":6},{"Year":1998,"Value":10},{"Year":1999,"Value":8},{"Year":2000,"Value":11},{"Year":2001,"Value":8},{"Year":2002,"Value":10},{"Year":2003,"Value":8},{"Year":2004,"Value":8},{"Year":2005,"Value":6},{"Year":2006,"Value":9},{"Year":2007,"Value":5},{"Year":2008,"Value":4},{"Year":2009,"Value":5},{"Year":2010,"Value":3},{"Year":2011,"Value":4},{"Year":2012,"Value":3},{"Year":2013,"Value":5},{"Year":2014,"Value":1},{"Year":2015,"Value":5},{"Year":2016,"Value":5},{"Year":2017,"Value":4},{"Year":2018,"Value":5}],"17-8-1":[{"Year":2012,"Value":97},{"Year":2013,"Value":97},{"Year":2014,"Value":99},{"Year":2017,"Value":99},{"Year":2018,"Value":99}],"3-5-2":[{"Year":1980,"Value":4.3},{"Year":1981,"Value":4.3},{"Year":1982,"Value":4.3},{"Year":1983,"Value":4.4},{"Year":1984,"Value":4.5},{"Year":1985,"Value":4.3},{"Year":1986,"Value":4.5},{"Year":1987,"Value":4.7},{"Year":1988,"Value":4.5},{"Year":1989,"Value":5.5},{"Year":1990,"Value":5.2},{"Year":1991,"Value":5.1},{"Year":1992,"Value":4.7},{"Year":1993,"Value":4.5},{"Year":1994,"Value":4.6},{"Year":1995,"Value":4.8},{"Year":1996,"Value":4.9},{"Year":1997,"Value":5.1},{"Year":1998,"Value":5.6},{"Year":1999,"Value":5.9},{"Year":2000,"Value":6.1},{"Year":2001,"Value":6.3},{"Year":2002,"Value":6.5},{"Year":2003,"Value":6.5},{"Year":2004,"Value":6.7},{"Year":2005,"Value":7.1},{"Year":2006,"Value":7.2},{"Year":2007,"Value":7.5},{"Year":2008,"Value":7.2},{"Year":2009,"Value":7.2},{"Year":2010,"Value":6.8},{"Year":2011,"Value":6.8},{"Year":2012,"Value":6.8},{"Year":2013,"Value":6.8},{"Year":2014,"Value":7.0},{"Year":2015,"Value":7.7},{"Year":2016,"Value":7.5},{"Year":2017,"Value":7.8},{"Year":2018,"Value":7.7}],"6-5-2":[{"Year":2015,"Value":2},{"Year":2016,"Value":2}],"12-4-1":[{"Year":2015,"Value":2},{"Year":2016,"Value":2}],"1-2-2":[{"Year":2009,"Value":4.2},{"Year":2010,"Value":3.4},{"Year":2011,"Value":1.8},{"Year":2012,"Value":2.1},{"Year":2013,"Value":2.4},{"Year":2014,"Value":2.3},{"Year":2015,"Value":2.9},{"Year":2016,"Value":1.5}],"9-2-2":[{"Year":1991,"Value":16.21621622},{"Year":1992,"Value":15.12052593},{"Year":1993,"Value":16.03221083},{"Year":1994,"Value":16.92084241},{"Year":1995,"Value":15.79689704},{"Year":1996,"Value":15.70422535},{"Year":1997,"Value":16.54929577},{"Year":1998,"Value":15.48343475},{"Year":1999,"Value":13.95955643},{"Year":2000,"Value":13.87468031},{"Year":2001,"Value":13.20754717},{"Year":2002,"Value":13.14613912},{"Year":2003,"Value":12.84987277},{"Year":2004,"Value":13.09904153},{"Year":2005,"Value":12.43811881},{"Year":2006,"Value":10.89517079},{"Year":2007,"Value":10.25352113},{"Year":2008,"Value":10.44109436},{"Year":2009,"Value":10.71428571},{"Year":2010,"Value":10.39426523},{"Year":2011,"Value":10.93189964},{"Year":2012,"Value":11.6499113},{"Year":2013,"Value":11.42857143},{"Year":2014,"Value":11.07986502},{"Year":2015,"Value":10.28851388},{"Year":2016,"Value":10.07345226},{"Year":2017,"Value":9.690721649},{"Year":2018,"Value":9.072580645}],"4-3-1":[{"Year":2015,"Value":2},{"Year":2016,"Value":2}],"12-2-2":[{"Year":2015,"Value":2},{"Year":2016,"Value":2}],"5-2-1":[{"Year":2015,"Value":5.0678733},{"Year":2016,"Value":5.2023121},{"Year":2017,"Value":4.8},{"Year":2018,"Value":6.1041293}],"15-6-1":[{"Year":2015,"Value":2},{"Year":2016,"Value":2}],"8-10-1":[{"Year":2015,"Value":2},{"Year":2016,"Value":2}],"14-1-1":[{"Year":2015,"Value":2},{"Year":2016,"Value":2}],"14-2-1":[{"Year":2015,"Value":2},{"Year":2016,"Value":2}],"14-5-1":[{"Year":2015,"Value":2},{"Year":2016,"Value":2}],"5-3-2":[{"Year":2015,"Value":2},{"Year":2016,"Value":2}],"4-6-1":[{"Year":2015,"Value":2},{"Year":2016,"Value":2}],"8-8-1":[{"Year":2015,"Value":2},{"Year":2016,"Value":2}],"17-16-1":[{"Year":2015,"Value":2},{"Year":2016,"Value":2}],"3-2-1":[{"Year":1961,"Value":23.7},{"Year":1962,"Value":21.4},{"Year":1963,"Value":22.2},{"Year":1964,"Value":21.7},{"Year":1965,"Value":20.5},{"Year":1966,"Value":17.3},{"Year":1967,"Value":16.6},{"Year":1968,"Value":18.0},{"Year":1969,"Value":14.7},{"Year":1970,"Value":15.9},{"Year":1971,"Value":16.4},{"Year":1972,"Value":13.0},{"Year":1973,"Value":12.6},{"Year":1974,"Value":14.5},{"Year":1975,"Value":16.7},{"Year":1976,"Value":10.3},{"Year":1977,"Value":12.5},{"Year":1978,"Value":13.7},{"Year":1979,"Value":null},{"Year":1980,"Value":9.7},{"Year":1981,"Value":7.4},{"Year":1982,"Value":8.3},{"Year":1983,"Value":7.5},{"Year":1984,"Value":6.8},{"Year":1985,"Value":8.0},{"Year":1986,"Value":6.0},{"Year":1987,"Value":8.1},{"Year":1988,"Value":7.5},{"Year":1989,"Value":6.1},{"Year":1990,"Value":6.7},{"Year":1991,"Value":6.8},{"Year":1992,"Value":6.5},{"Year":1993,"Value":5.6},{"Year":1994,"Value":3.8},{"Year":1995,"Value":8.6},{"Year":1996,"Value":4.6},{"Year":1997,"Value":6.3},{"Year":1998,"Value":4.8},{"Year":1999,"Value":2.4},{"Year":2000,"Value":3.9},{"Year":2001,"Value":3.4},{"Year":2002,"Value":3.7},{"Year":2003,"Value":2.9},{"Year":2004,"Value":3.1},{"Year":2005,"Value":3.0},{"Year":2006,"Value":2.3},{"Year":2007,"Value":3.3},{"Year":2008,"Value":3.5},{"Year":2009,"Value":2.2},{"Year":2010,"Value":3.3},{"Year":2011,"Value":1.6},{"Year":2012,"Value":1.5},{"Year":2013,"Value":2.5},{"Year":2014,"Value":2.3},{"Year":2015,"Value":3.1},{"Year":2016,"Value":2.0},{"Year":2017,"Value":3.4}],"7-b-1":[{"Year":2015,"Value":2},{"Year":2016,"Value":2}],"2-3-2":[{"Year":2015,"Value":2},{"Year":2016,"Value":2}],"3-a-1":[],"14-4-1":[{"Year":2015,"Value":2},{"Year":2016,"Value":2}],"10-1-1":[{"Year":2015,"Value":2},{"Year":2016,"Value":2}],"1-5-1":[{"Year":2015,"Value":2},{"Year":2016,"Value":2}],"16-1-3":[{"Year":2015,"Value":2},{"Year":2016,"Value":2}],"17-10-1":[{"Year":2015,"Value":2},{"Year":2016,"Value":2}],"11-5-2":[{"Year":1987,"Value":0.0131},{"Year":1988,"Value":0.0636},{"Year":1989,"Value":0.0351},{"Year":1990,"Value":0.146},{"Year":1991,"Value":0.0268},{"Year":1992,"Value":0.0175},{"Year":1993,"Value":0.0081},{"Year":1994,"Value":0.1961},{"Year":1995,"Value":0.7583},{"Year":1996,"Value":0.2841},{"Year":1997,"Value":0.0045},{"Year":1998,"Value":0.0142},{"Year":1999,"Value":0.0193},{"Year":2000,"Value":1.2552},{"Year":2001,"Value":0.0006},{"Year":2002,"Value":0.0132},{"Year":2003,"Value":0.0004},{"Year":2004,"Value":0.0092},{"Year":2005,"Value":0.0014},{"Year":2006,"Value":0.0437},{"Year":2007,"Value":0.0024},{"Year":2008,"Value":1.0626},{"Year":2009,"Value":0.0042},{"Year":2010,"Value":0.0215},{"Year":2011,"Value":0.0343},{"Year":2012,"Value":0.0006},{"Year":2013,"Value":0.0002},{"Year":2014,"Value":0.0003},{"Year":2015,"Value":0.016},{"Year":2016,"Value":0.0002},{"Year":2017,"Value":0.0082},{"Year":2018,"Value":0.0011}],"9-2-1":[{"Year":2015,"Value":2},{"Year":2016,"Value":2}],"9-1-2":[{"Year":2015,"Value":2},{"Year":2016,"Value":2}],"2-2-2":[{"Year":2015,"Value":2},{"Year":2016,"Value":2}],"5-a-1":[{"Year":2015,"Value":2},{"Year":2016,"Value":2}],"1-5-3":[{"Year":2015,"Value":2},{"Year":2016,"Value":2}],"16-7-2":[{"Year":2015,"Value":2},{"Year":2016,"Value":2}],"15-4-2":[{"Year":2016,"Value":31}],"2-1-2":[{"Year":2015,"Value":2},{"Year":2016,"Value":2}],"11-3-2":[{"Year":2015,"Value":2},{"Year":2016,"Value":2}],"15-3-1":[{"Year":2015,"Value":2},{"Year":2016,"Value":2}],"15-9-1":[{"Year":2015,"Value":2},{"Year":2016,"Value":2}],"5-c-1":[{"Year":2015,"Value":2},{"Year":2016,"Value":2}],"1-a-2":[{"Year":1998,"Units":"Percentage (%) of national budget","Value":54.56},{"Year":1999,"Units":"Percentage (%) of national budget","Value":55.31},{"Year":2000,"Units":"Percentage (%) of national budget","Value":55.13},{"Year":2001,"Units":"Percentage (%) of national budget","Value":55.03},{"Year":2002,"Units":"Percentage (%) of national budget","Value":57.54},{"Year":2003,"Units":"Percentage (%) of national budget","Value":58.53},{"Year":2004,"Units":"Percentage (%) of national budget","Value":59.02},{"Year":2005,"Units":"Percentage (%) of national budget","Value":60.13},{"Year":2006,"Units":"Percentage (%) of national budget","Value":58.61},{"Year":2007,"Units":"Percentage (%) of national budget","Value":57.71},{"Year":2008,"Units":"Percentage (%) of national budget","Value":43.71},{"Year":2009,"Units":"Percentage (%) of national budget","Value":55.1},{"Year":2010,"Units":"Percentage (%) of national budget","Value":53.0},{"Year":2011,"Units":"Percentage (%) of national budget","Value":57.36},{"Year":2012,"Units":"Percentage (%) of national budget","Value":56.46},{"Year":2013,"Units":"Percentage (%) of national budget","Value":57.09},{"Year":2014,"Units":"Percentage (%) of national budget","Value":55.84},{"Year":2015,"Units":"Percentage (%) of national budget","Value":56.84},{"Year":2016,"Units":"Percentage (%) of national budget","Value":52.49},{"Year":2017,"Units":"Percentage (%) of national budget","Value":57.37},{"Year":1998,"Units":"Percentage (%) of Gross Domestic Product (GDP)","Value":22.18},{"Year":1999,"Units":"Percentage (%) of Gross Domestic Product (GDP)","Value":22.88},{"Year":2000,"Units":"Percentage (%) of Gross Domestic Product (GDP)","Value":22.59},{"Year":2001,"Units":"Percentage (%) of Gross Domestic Product (GDP)","Value":22.85},{"Year":2002,"Units":"Percentage (%) of Gross Domestic Product (GDP)","Value":24.64},{"Year":2003,"Units":"Percentage (%) of Gross Domestic Product (GDP)","Value":25.93},{"Year":2004,"Units":"Percentage (%) of Gross Domestic Product (GDP)","Value":25.14},{"Year":2005,"Units":"Percentage (%) of Gross Domestic Product (GDP)","Value":24.84},{"Year":2006,"Units":"Percentage (%) of Gross Domestic Product (GDP)","Value":23.87},{"Year":2007,"Units":"Percentage (%) of Gross Domestic Product (GDP)","Value":23.42},{"Year":2008,"Units":"Percentage (%) of Gross Domestic Product (GDP)","Value":23.83},{"Year":2009,"Units":"Percentage (%) of Gross Domestic Product (GDP)","Value":26.11},{"Year":2010,"Units":"Percentage (%) of Gross Domestic Product (GDP)","Value":25.33},{"Year":2011,"Units":"Percentage (%) of Gross Domestic Product (GDP)","Value":25.37},{"Year":2012,"Units":"Percentage (%) of Gross Domestic Product (GDP)","Value":24.74},{"Year":2013,"Units":"Percentage (%) of Gross Domestic Product (GDP)","Value":24.21},{"Year":2014,"Units":"Percentage (%) of Gross Domestic Product (GDP)","Value":24.47},{"Year":2015,"Units":"Percentage (%) of Gross Domestic Product (GDP)","Value":23.59},{"Year":2016,"Units":"Percentage (%) of Gross Domestic Product (GDP)","Value":23.26},{"Year":2017,"Units":"Percentage (%) of Gross Domestic Product (GDP)","Value":24.83}],"8-9-2":[{"Year":2015,"Value":2},{"Year":2016,"Value":2}],"17-12-1":[{"Year":2015,"Value":2},{"Year":2016,"Value":2}],"5-1-1":[{"Year":2015,"Value":2},{"Year":2016,"Value":2}],"11-b-2":[{"Year":2015,"Value":2},{"Year":2016,"Value":2}],"3-3-1":[{"Year":1983,"Value":0.004245617},{"Year":1984,"Value":0.0},{"Year":1985,"Value":0.066498757},{"Year":1986,"Value":0.053673984},{"Year":1987,"Value":0.020478626},{"Year":1988,"Value":0.05251231},{"Year":1989,"Value":0.023817179},{"Year":1990,"Value":0.019701716},{"Year":1991,"Value":0.039082957},{"Year":1992,"Value":0.042352162},{"Year":1993,"Value":0.011433537},{"Year":1994,"Value":0.03018139},{"Year":1995,"Value":0.026219389},{"Year":1996,"Value":0.022391569},{"Year":1997,"Value":0.033348896},{"Year":1998,"Value":0.029370624},{"Year":1999,"Value":0.043523677},{"Year":2000,"Value":0.035836},{"Year":2001,"Value":0.038819739},{"Year":2002,"Value":0.024426415},{"Year":2003,"Value":0.03466553},{"Year":2004,"Value":0.017207558},{"Year":2005,"Value":0.027250091},{"Year":2006,"Value":0.036679994},{"Year":2007,"Value":0.042252789},{"Year":2008,"Value":0.031699841},{"Year":2009,"Value":0.046967761},{"Year":2010,"Value":0.075559613},{"Year":2011,"Value":0.072224385},{"Year":2012,"Value":0.062583118},{"Year":2013,"Value":0.034176669},{"Year":2014,"Value":0.030705835},{"Year":2015,"Value":0.039501671},{"Year":2016,"Value":0.081195926},{"Year":2017,"Value":0.082754789},{"Year":2018,"Value":0.109054384}],"17-15-1":[{"Year":2015,"Value":2},{"Year":2016,"Value":2}],"6-6-1":[],"11-7-1":[{"Year":2000,"Value":7.967725668},{"Year":2006,"Value":6.785270997},{"Year":2012,"Value":7.237687366},{"Year":2018,"Value":6.845238095}],"9-a-1":[{"Year":2015,"Value":2},{"Year":2016,"Value":2}],"3-2-2":[{"Year":1951,"Value":12.8},{"Year":1952,"Value":11.0},{"Year":1953,"Value":12.7},{"Year":1954,"Value":11.0},{"Year":1955,"Value":12.7},{"Year":1956,"Value":10.9},{"Year":1957,"Value":9.7},{"Year":1958,"Value":13.6},{"Year":1959,"Value":8.9},{"Year":1960,"Value":9.2},{"Year":1961,"Value":14.7},{"Year":1962,"Value":10.8},{"Year":1963,"Value":11.2},{"Year":1964,"Value":12.5},{"Year":1965,"Value":10.6},{"Year":1966,"Value":9.8},{"Year":1967,"Value":10.0},{"Year":1968,"Value":12.3},{"Year":1969,"Value":8.3},{"Year":1970,"Value":10.2},{"Year":1971,"Value":9.8},{"Year":1972,"Value":9.6},{"Year":1973,"Value":7.8},{"Year":1974,"Value":10.1},{"Year":1975,"Value":8.9},{"Year":1976,"Value":4.4},{"Year":1977,"Value":7.0},{"Year":1978,"Value":6.2},{"Year":1979,"Value":4.7},{"Year":1980,"Value":6.0},{"Year":1981,"Value":3.7},{"Year":1982,"Value":4.6},{"Year":1983,"Value":5.3},{"Year":1984,"Value":3.6},{"Year":1985,"Value":3.6},{"Year":1986,"Value":3.9},{"Year":1987,"Value":5.0},{"Year":1988,"Value":4.1},{"Year":1989,"Value":3.3},{"Year":1990,"Value":4.0},{"Year":1991,"Value":2.9},{"Year":1992,"Value":3.7},{"Year":1993,"Value":2.8},{"Year":1994,"Value":1.1},{"Year":1995,"Value":4.4},{"Year":1996,"Value":3.0},{"Year":1997,"Value":3.1},{"Year":1998,"Value":2.2},{"Year":1999,"Value":1.5},{"Year":2000,"Value":2.5},{"Year":2001,"Value":2.0},{"Year":2002,"Value":1.2},{"Year":2003,"Value":1.9},{"Year":2004,"Value":1.4},{"Year":2005,"Value":1.6},{"Year":2006,"Value":0.9},{"Year":2007,"Value":1.3},{"Year":2008,"Value":1.7},{"Year":2009,"Value":1.0},{"Year":2010,"Value":1.2},{"Year":2011,"Value":0.7},{"Year":2012,"Value":0.7},{"Year":2013,"Value":1.4},{"Year":2014,"Value":1.6},{"Year":2015,"Value":1.4},{"Year":2016,"Value":0.5},{"Year":2017,"Value":2.2}],"8-a-1":[{"Year":2015,"Value":2},{"Year":2016,"Value":2}],"9-3-2":[{"Year":2015,"Value":2},{"Year":2016,"Value":2}],"1-5-2":[{"Year":1987,"Value":0.0131},{"Year":1988,"Value":0.0636},{"Year":1989,"Value":0.0351},{"Year":1990,"Value":0.146},{"Year":1991,"Value":0.0268},{"Year":1992,"Value":0.0175},{"Year":1993,"Value":0.0081},{"Year":1994,"Value":0.1961},{"Year":1995,"Value":0.7583},{"Year":1996,"Value":0.2841},{"Year":1997,"Value":0.0045},{"Year":1998,"Value":0.0142},{"Year":1999,"Value":0.0193},{"Year":2000,"Value":1.2552},{"Year":2001,"Value":0.0006},{"Year":2002,"Value":0.0132},{"Year":2003,"Value":0.0004},{"Year":2004,"Value":0.0092},{"Year":2005,"Value":0.0014},{"Year":2006,"Value":0.0437},{"Year":2007,"Value":0.0024},{"Year":2008,"Value":1.0626},{"Year":2009,"Value":0.0042},{"Year":2010,"Value":0.0215},{"Year":2011,"Value":0.0343},{"Year":2012,"Value":0.0006},{"Year":2013,"Value":0.0002},{"Year":2014,"Value":0.0003},{"Year":2015,"Value":0.016},{"Year":2016,"Value":0.0002},{"Year":2017,"Value":0.0082},{"Year":2018,"Value":0.0011}],"1-2-1":[{"Year":2004,"Value":10.0},{"Year":2005,"Value":9.7},{"Year":2006,"Value":9.6},{"Year":2007,"Value":10.1},{"Year":2008,"Value":10.1},{"Year":2009,"Value":10.2},{"Year":2010,"Value":9.8},{"Year":2011,"Value":9.2},{"Year":2012,"Value":7.9},{"Year":2013,"Value":9.3},{"Year":2014,"Value":7.9},{"Year":2015,"Value":9.2},{"Year":2016,"Value":8.8}],"17-6-1":[{"Year":2015,"Value":2},{"Year":2016,"Value":2}],"3-5-1":[{"Year":2015,"Value":2},{"Year":2016,"Value":2}],"1-5-4":[{"Year":2015,"Value":2},{"Year":2016,"Value":2}],"14-6-1":[{"Year":2015,"Value":2},{"Year":2016,"Value":2}],"3-c-1":[{"Year":2015,"Value":2},{"Year":2016,"Value":2}],"11-c-1":[{"Year":2015,"Value":2},{"Year":2016,"Value":2}],"3-b-3":[{"Year":2015,"Value":2},{"Year":2016,"Value":2}],"12-4-2":[{"Year":2015,"Value":2},{"Year":2016,"Value":2}],"10-c-1":[{"Year":2015,"Value":2},{"Year":2016,"Value":2}],"10-5-1":[{"Year":2015,"Value":2},{"Year":2016,"Value":2}],"8-1-1":[{"Year":1946,"Value":2.5},{"Year":1947,"Value":8.8},{"Year":1948,"Value":-0.2},{"Year":1949,"Value":-3.8},{"Year":1950,"Value":-4.2},{"Year":1951,"Value":-3.9},{"Year":1952,"Value":-2.6},{"Year":1953,"Value":13.1},{"Year":1954,"Value":6.7},{"Year":1955,"Value":7.3},{"Year":1956,"Value":0.3},{"Year":1957,"Value":-2.3},{"Year":1958,"Value":5.5},{"Year":1959,"Value":-0.1},{"Year":1960,"Value":1.1},{"Year":1961,"Value":-1.8},{"Year":1962,"Value":6.4},{"Year":1963,"Value":8.2},{"Year":1964,"Value":8.0},{"Year":1965,"Value":5.4},{"Year":1966,"Value":6.9},{"Year":1967,"Value":-2.8},{"Year":1968,"Value":-6.7},{"Year":1969,"Value":1.5},{"Year":1970,"Value":6.8},{"Year":1971,"Value":12.0},{"Year":1972,"Value":4.6},{"Year":1973,"Value":5.3},{"Year":1974,"Value":4.3},{"Year":1975,"Value":-0.6},{"Year":1976,"Value":4.9},{"Year":1977,"Value":8.0},{"Year":1978,"Value":5.2},{"Year":1979,"Value":3.9},{"Year":1980,"Value":4.6},{"Year":1981,"Value":3.1},{"Year":1982,"Value":0.8},{"Year":1983,"Value":-3.4},{"Year":1984,"Value":3.1},{"Year":1985,"Value":2.5},{"Year":1986,"Value":5.5},{"Year":1987,"Value":7.3},{"Year":1988,"Value":-1.7},{"Year":1989,"Value":-0.9},{"Year":1990,"Value":0.4},{"Year":1991,"Value":-1.5},{"Year":1992,"Value":-4.5},{"Year":1993,"Value":0.3},{"Year":1994,"Value":2.7},{"Year":1995,"Value":-0.4},{"Year":1996,"Value":4.2},{"Year":1997,"Value":3.2},{"Year":1998,"Value":6.0},{"Year":1999,"Value":2.8},{"Year":2000,"Value":3.4},{"Year":2001,"Value":2.5},{"Year":2002,"Value":-0.2},{"Year":2003,"Value":1.7},{"Year":2004,"Value":6.8},{"Year":2005,"Value":5.2},{"Year":2006,"Value":2.3},{"Year":2007,"Value":6.9},{"Year":2008,"Value":-0.5},{"Year":2009,"Value":-6.7},{"Year":2010,"Value":-3.1},{"Year":2011,"Value":1.6},{"Year":2012,"Value":0.8},{"Year":2013,"Value":3.2},{"Year":2014,"Value":1.0},{"Year":2015,"Value":3.7},{"Year":2016,"Value":5.2},{"Year":2017,"Value":2.2},{"Year":2018,"Value":1.7}],"15-5-1":[{"Year":2015,"Value":2},{"Year":2016,"Value":2}],"17-19-2":[{"Year":2015,"Value":2},{"Year":2016,"Value":2}],"3-b-2":[{"Year":2015,"Value":2},{"Year":2016,"Value":2}],"13-1-3":[{"Year":2015,"Value":2},{"Year":2016,"Value":2}],"15-c-1":[{"Year":2015,"Value":2},{"Year":2016,"Value":2}],"15-4-1":[{"Year":2015,"Value":2},{"Year":2016,"Value":2}],"8-10-2":[{"Year":2015,"Value":2},{"Year":2016,"Value":2}],"12-b-1":[{"Year":2015,"Value":2},{"Year":2016,"Value":2}],"6-3-1":[{"Year":2015,"Value":2},{"Year":2016,"Value":2}],"16-5-1":[{"Year":2015,"Value":2},{"Year":2016,"Value":2}],"1-a-3":[{"Year":2015,"Value":2},{"Year":2016,"Value":2}],"3-9-2":[{"Year":1996,"Value":0.746385628},{"Year":1997,"Value":0.370543291},{"Year":1998,"Value":0.734265606},{"Year":1999,"Value":1.088091922},{"Year":2000,"Value":0.716720003},{"Year":2001,"Value":0.352906716},{"Year":2002,"Value":0.348948792},{"Year":2003,"Value":0.693310593},{"Year":2004,"Value":1.032453454},{"Year":2005,"Value":0.681252278},{"Year":2006,"Value":1.000363465},{"Year":2007,"Value":0.975064354},{"Year":2008,"Value":2.535987244},{"Year":2009,"Value":0.626236818},{"Year":2010,"Value":0.314831722},{"Year":2011,"Value":1.884114403},{"Year":2012,"Value":1.877493546},{"Year":2013,"Value":1.864181919},{"Year":2014,"Value":2.456466802},{"Year":2015,"Value":2.430872075},{"Year":2016,"Value":2.405805208},{"Year":2017,"Value":2.659975351}],"14-7-1":[{"Year":2015,"Value":2},{"Year":2016,"Value":2}],"17-7-1":[{"Year":2015,"Value":2},{"Year":2016,"Value":2}],"12-7-1":[{"Year":2015,"Value":2},{"Year":2016,"Value":2}],"3-3-3":[{"Year":2011,"Value":0.31},{"Year":2012,"Value":null},{"Year":2013,"Value":1.85},{"Year":2014,"Value":1.22},{"Year":2015,"Value":0.3},{"Year":2016,"Value":0.6},{"Year":2017,"Value":0.87},{"Year":2018,"Value":0.9}],"17-18-1":[{"Year":2015,"Value":2},{"Year":2016,"Value":2}],"14-c-1":[{"Year":2015,"Value":2},{"Year":2016,"Value":2}],"15-7-1":[{"Year":2015,"Value":2},{"Year":2016,"Value":2}],"16-2-3":[{"Year":2015,"Value":2},{"Year":2016,"Value":2}],"3-7-1":[{"Year":2015,"Value":2},{"Year":2016,"Value":2}],"17-17-1":[{"Year":2015,"Value":2},{"Year":2016,"Value":2}],"3-7-2":[{"Year":2000,"Value":22.8},{"Year":2001,"Value":19.7},{"Year":2002,"Value":18.2},{"Year":2003,"Value":16.4},{"Year":2004,"Value":13.0},{"Year":2005,"Value":15.1},{"Year":2006,"Value":14.4},{"Year":2007,"Value":14.2},{"Year":2008,"Value":14.6},{"Year":2009,"Value":14.3},{"Year":2010,"Value":12.9},{"Year":2011,"Value":10.8},{"Year":2012,"Value":11.0},{"Year":2013,"Value":7.1},{"Year":2014,"Value":7.5},{"Year":2015,"Value":7.9},{"Year":2016,"Value":6.5},{"Year":2017,"Value":5.9},{"Year":2018,"Value":5.3}],"16-1-4":[{"Year":2015,"Value":2},{"Year":2016,"Value":2}],"5-6-2":[{"Year":2015,"Value":2},{"Year":2016,"Value":2}],"3-3-4":[{"Year":2010,"Value":8.18},{"Year":2011,"Value":6.58},{"Year":2012,"Value":6.24},{"Year":2013,"Value":4.94},{"Year":2014,"Value":8.86},{"Year":2015,"Value":5.14},{"Year":2016,"Value":17.59},{"Year":2017,"Value":20.4},{"Year":2018,"Value":13.7}],"6-2-1":[{"Year":2015,"Value":2},{"Year":2016,"Value":2}],"3-9-3":[{"Year":1996,"Value":0.373192814},{"Year":1997,"Value":0.0},{"Year":1998,"Value":2.569929621},{"Year":1999,"Value":0.0},{"Year":2000,"Value":0.716720003},{"Year":2001,"Value":2.117440297},{"Year":2002,"Value":0.348948792},{"Year":2003,"Value":0.693310593},{"Year":2004,"Value":0.0},{"Year":2005,"Value":0.681252278},{"Year":2006,"Value":0.333454488},{"Year":2007,"Value":0.0},{"Year":2008,"Value":0.950995216},{"Year":2009,"Value":0.626236818},{"Year":2010,"Value":0.629663445},{"Year":2011,"Value":1.884114403},{"Year":2012,"Value":1.564577955},{"Year":2013,"Value":0.93209096},{"Year":2014,"Value":0.921175051},{"Year":2015,"Value":0.607718019},{"Year":2016,"Value":0.0},{"Year":2017,"Value":1.477764084}],"2-b-1":[{"Year":2015,"Value":2},{"Year":2016,"Value":2}],"3-1-1":[{"Year":2015,"Value":2},{"Year":2016,"Value":2}],"16-2-2":[{"Year":2015,"Value":2},{"Year":2016,"Value":2}],"16-b-1":[{"Year":2015,"Value":2},{"Year":2016,"Value":2}],"5-5-1":[],"8-5-1":[{"Year":2015,"Value":2},{"Year":2016,"Value":2}],"2-3-1":[{"Year":2015,"Value":2},{"Year":2016,"Value":2}],"9-4-1":[{"Year":1997,"Value":0.414078362},{"Year":1998,"Value":0.394027708},{"Year":1999,"Value":0.405018556},{"Year":2000,"Value":0.435865179},{"Year":2001,"Value":0.511642878},{"Year":2002,"Value":0.467209132},{"Year":2003,"Value":0.387678626},{"Year":2004,"Value":0.329308438},{"Year":2005,"Value":0.300784685},{"Year":2006,"Value":0.305819215},{"Year":2007,"Value":0.2431074},{"Year":2008,"Value":0.306095378},{"Year":2009,"Value":0.454821752},{"Year":2010,"Value":0.477854844},{"Year":2011,"Value":0.418137457},{"Year":2012,"Value":0.447299476},{"Year":2013,"Value":0.397326422},{"Year":2014,"Value":0.372563342},{"Year":2015,"Value":0.401640803},{"Year":2016,"Value":0.351121205},{"Year":2017,"Value":0.345424968}],"9-1-1":[{"Year":2015,"Value":2},{"Year":2016,"Value":2}],"8-9-1":[{"Year":2009,"Value":3.5},{"Year":2010,"Value":3.4},{"Year":2011,"Value":3.7},{"Year":2012,"Value":4.2},{"Year":2013,"Value":4.7},{"Year":2014,"Value":5.2},{"Year":2015,"Value":6.2},{"Year":2016,"Value":8.1},{"Year":2017,"Value":8.6}],"10-a-1":[{"Year":2015,"Value":2},{"Year":2016,"Value":2}],"4-2-1":[{"Year":2015,"Value":2},{"Year":2016,"Value":2}],"1-3-1":[{"Year":2015,"Value":2},{"Year":2016,"Value":2}],"13-1-2":[{"Year":2015,"Value":2},{"Year":2016,"Value":2}],"12-8-1":[{"Year":2015,"Value":2},{"Year":2016,"Value":2}],"2-1-1":[{"Year":2015,"Value":2},{"Year":2016,"Value":2}],"2-a-1":[{"Year":2001,"Value":0.628658103},{"Year":2002,"Value":0.605942664},{"Year":2003,"Value":0.700889093},{"Year":2004,"Value":0.769692413},{"Year":2005,"Value":0.820962752},{"Year":2006,"Value":0.792588461},{"Year":2007,"Value":0.829894318},{"Year":2008,"Value":0.515927917},{"Year":2009,"Value":0.523787317},{"Year":2010,"Value":0.451847994},{"Year":2011,"Value":0.465998097},{"Year":2012,"Value":0.486652369},{"Year":2013,"Value":0.49227752},{"Year":2014,"Value":0.512328719},{"Year":2015,"Value":0.496803882},{"Year":2016,"Value":0.483073089}],"12-1-1":[{"Year":2015,"Value":2},{"Year":2016,"Value":2}],"8-6-1":[{"Year":2003,"Value":4.9},{"Year":2004,"Value":5.5},{"Year":2005,"Value":4.6},{"Year":2006,"Value":4.7},{"Year":2007,"Value":4.0},{"Year":2008,"Value":4.5},{"Year":2009,"Value":7.7},{"Year":2010,"Value":7.4},{"Year":2011,"Value":6.7},{"Year":2012,"Value":5.9},{"Year":2013,"Value":5.5},{"Year":2014,"Value":5.7},{"Year":2015,"Value":4.6},{"Year":2016,"Value":4.1},{"Year":2017,"Value":3.9},{"Year":2018,"Value":4.9}],"4-1-1":[{"Year":2015,"Value":2},{"Year":2016,"Value":2}],"8-4-1":[{"Year":2015,"Value":2},{"Year":2016,"Value":2}],"11-2-1":[{"Year":2015,"Value":2},{"Year":2016,"Value":2}],"17-19-1":[{"Year":2015,"Value":2},{"Year":2016,"Value":2}],"3-b-1":[],"17-4-1":[{"Year":2015,"Value":2},{"Year":2016,"Value":2}],"12-3-1":[{"Year":2015,"Value":2},{"Year":2016,"Value":2}],"16-10-1":[{"Year":2015,"Value":2},{"Year":2016,"Value":2}],"6-1-1":[{"Year":2015,"Value":2},{"Year":2016,"Value":2}],"10-7-2":[{"Year":2015,"Value":2},{"Year":2016,"Value":2}],"16-1-2":[{"Year":2015,"Value":2},{"Year":2016,"Value":2}],"17-18-3":[{"Year":2015,"Value":2},{"Year":2016,"Value":2}],"13-a-1":[{"Year":2015,"Value":2},{"Year":2016,"Value":2}],"11-6-1":[{"Year":2015,"Value":2},{"Year":2016,"Value":2}],"7-a-1":[{"Year":2015,"Value":2},{"Year":2016,"Value":2}],"3-8-1":[{"Year":2015,"Value":2},{"Year":2016,"Value":2}],"16-a-1":[{"Year":2015,"Value":2},{"Year":2016,"Value":2}],"17-5-1":[{"Year":2015,"Value":2},{"Year":2016,"Value":2}],"6-5-1":[{"Year":2015,"Value":2},{"Year":2016,"Value":2}],"17-1-1":[],"7-3-1":[{"Year":1990,"Value":12.8},{"Year":1991,"Value":11.7},{"Year":1992,"Value":11.8},{"Year":1993,"Value":12.6},{"Year":1994,"Value":12.3},{"Year":1995,"Value":12.3},{"Year":1996,"Value":12.6},{"Year":1997,"Value":11.8},{"Year":1998,"Value":11.8},{"Year":1999,"Value":12.7},{"Year":2000,"Value":13.6},{"Year":2001,"Value":12.7},{"Year":2002,"Value":13.0},{"Year":2003,"Value":12.7},{"Year":2004,"Value":11.6},{"Year":2005,"Value":11.1},{"Year":2006,"Value":13.1},{"Year":2007,"Value":14.2},{"Year":2008,"Value":15.8},{"Year":2009,"Value":17.6},{"Year":2010,"Value":18.4},{"Year":2011,"Value":19.3},{"Year":2012,"Value":18.6},{"Year":2013,"Value":18.5},{"Year":2014,"Value":18.1},{"Year":2015,"Value":16.6}],"17-3-1":[{"Year":2015,"Value":2},{"Year":2016,"Value":2}],"8-8-2":[{"Year":2015,"Value":2},{"Year":2016,"Value":2}],"16-1-1":[{"Year":2015,"Value":2},{"Year":2016,"Value":2}],"12-a-1":[{"Year":2015,"Value":2},{"Year":2016,"Value":2}],"6-4-1":[{"Year":2015,"Value":2},{"Year":2016,"Value":2}],"10-2-1":[{"Year":2015,"Value":2},{"Year":2016,"Value":2}],"11-7-2":[{"Year":2015,"Value":2},{"Year":2016,"Value":2}],"17-13-1":[{"Year":2015,"Value":2},{"Year":2016,"Value":2}],"2-4-1":[{"Year":2015,"Value":2},{"Year":2016,"Value":2}],"10-3-1":[{"Year":2015,"Value":2},{"Year":2016,"Value":2}],"4-2-2":[{"Year":1998,"Value":0.911578026},{"Year":1999,"Value":0.9252693},{"Year":2000,"Value":0.944765426},{"Year":2001,"Value":0.933197464},{"Year":2002,"Value":0.952662722},{"Year":2003,"Value":0.954641598},{"Year":2004,"Value":0.960643149},{"Year":2005,"Value":0.963741339},{"Year":2006,"Value":0.945410628},{"Year":2007,"Value":0.964857004},{"Year":2008,"Value":0.945147679},{"Year":2009,"Value":0.951469583},{"Year":2010,"Value":0.958323739},{"Year":2011,"Value":0.981460547},{"Year":2012,"Value":0.993146142},{"Year":2013,"Value":0.965086754},{"Year":2014,"Value":0.976410256},{"Year":2015,"Value":0.974036678},{"Year":2016,"Value":0.977723864},{"Year":2017,"Value":0.973460953},{"Year":2018,"Value":0.967032967}],"16-4-2":[{"Year":2015,"Value":2},{"Year":2016,"Value":2}],"5-3-1":[],"12-c-1":[{"Year":2015,"Value":2},{"Year":2016,"Value":2}],"13-b-1":[{"Year":2015,"Value":2},{"Year":2016,"Value":2}],"16-7-1":[{"Year":2015,"Value":2},{"Year":2016,"Value":2}],"13-3-1":[{"Year":2015,"Value":2},{"Year":2016,"Value":2}],"16-3-2":[{"Year":2015,"Value":2},{"Year":2016,"Value":2}],"9-5-1":[{"Year":2013,"Value":1.76},{"Year":2014,"Value":2.01},{"Year":2015,"Value":2.2},{"Year":2016,"Value":2.12},{"Year":2017,"Value":2.1}],"4-4-1":[],"16-10-2":[{"Year":2015,"Value":2},{"Year":2016,"Value":2}],"15-2-1":[],"3-1-2":[{"Year":1990,"Value":100.0},{"Year":1991,"Value":99.9},{"Year":1992,"Value":99.8},{"Year":1993,"Value":99.8},{"Year":1994,"Value":99.8},{"Year":1995,"Value":99.8},{"Year":1996,"Value":99.8},{"Year":1997,"Value":99.8},{"Year":1998,"Value":99.9},{"Year":1999,"Value":99.6},{"Year":2000,"Value":99.3},{"Year":2001,"Value":99.5},{"Year":2002,"Value":99.4},{"Year":2003,"Value":99.4},{"Year":2004,"Value":99.4},{"Year":2005,"Value":99.0},{"Year":2006,"Value":98.9},{"Year":2007,"Value":98.9},{"Year":2008,"Value":98.7},{"Year":2009,"Value":98.8},{"Year":2010,"Value":98.2},{"Year":2011,"Value":97.9},{"Year":2012,"Value":97.8},{"Year":2013,"Value":98.1},{"Year":2014,"Value":97.8},{"Year":2015,"Value":98.2},{"Year":2016,"Value":97.9}],"5-2-2":[{"Year":2013,"Value":1.6773163},{"Year":2014,"Value":2.9411765},{"Year":2015,"Value":3.5},{"Year":2016,"Value":2.6720648},{"Year":2017,"Value":4.3189369},{"Year":2018,"Value":4.1237113}],"16-8-1":[{"Year":2015,"Value":2},{"Year":2016,"Value":2}],"6-3-2":[{"Year":2015,"Value":2},{"Year":2016,"Value":2}],"5-b-1":[],"16-5-2":[{"Year":2015,"Value":2},{"Year":2016,"Value":2}],"16-6-2":[{"Year":2015,"Value":2},{"Year":2016,"Value":2}],"2-2-1":[{"Year":2015,"Value":2},{"Year":2016,"Value":2}],"8-3-1":[{"Year":2015,"Value":2},{"Year":2016,"Value":2}],"17-9-1":[{"Year":2015,"Value":2},{"Year":2016,"Value":2}],"6-a-1":[{"Year":2015,"Value":2},{"Year":2016,"Value":2}],"16-2-1":[{"Year":2015,"Value":2},{"Year":2016,"Value":2}],"12-5-1":[{"Year":2008,"Value":19},{"Year":2009,"Value":20},{"Year":2010,"Value":21},{"Year":2011,"Value":25},{"Year":2012,"Value":28},{"Year":2013,"Value":30},{"Year":2014,"Value":30},{"Year":2015,"Value":28},{"Year":2016,"Value":33},{"Year":2017,"Value":26}],"6-b-1":[{"Year":2015,"Value":2},{"Year":2016,"Value":2}],"1-4-1":[{"Year":2011,"Value":99.8}],"9-5-2":[{"Year":2015,"Value":2},{"Year":2016,"Value":2}],"17-11-1":[],"17-1-2":[{"Year":1998,"Value":82.81542066},{"Year":1999,"Value":86.93826921},{"Year":2000,"Value":87.79910742},{"Year":2001,"Value":82.33812484},{"Year":2002,"Value":79.05642639},{"Year":2003,"Value":79.71239046},{"Year":2004,"Value":85.25455618},{"Year":2005,"Value":95.42335561},{"Year":2006,"Value":98.69124952},{"Year":2007,"Value":95.24157694},{"Year":2008,"Value":63.46843603},{"Year":2009,"Value":65.94708333},{"Year":2010,"Value":67.75611312},{"Year":2011,"Value":75.37686115},{"Year":2012,"Value":77.60499189},{"Year":2013,"Value":81.41090629},{"Year":2014,"Value":85.22620201},{"Year":2015,"Value":85.55260313},{"Year":2016,"Value":114.1511825},{"Year":2017,"Value":87.42822118},{"Year":2018,"Value":87.89234326}],"8-5-2":[{"Year":1991,"Value":2.5},{"Year":1992,"Value":4.3},{"Year":1993,"Value":5.3},{"Year":1994,"Value":5.3},{"Year":1995,"Value":4.9},{"Year":1996,"Value":3.7},{"Year":1997,"Value":3.9},{"Year":1998,"Value":2.7},{"Year":1999,"Value":2.0},{"Year":2000,"Value":2.3},{"Year":2001,"Value":2.3},{"Year":2002,"Value":3.3},{"Year":2003,"Value":3.3},{"Year":2004,"Value":3.1},{"Year":2005,"Value":2.6},{"Year":2006,"Value":2.9},{"Year":2007,"Value":2.3},{"Year":2008,"Value":3.0},{"Year":2009,"Value":7.2},{"Year":2010,"Value":7.6},{"Year":2011,"Value":7.1},{"Year":2012,"Value":6.0},{"Year":2013,"Value":5.4},{"Year":2014,"Value":5.0},{"Year":2015,"Value":4.0},{"Year":2016,"Value":3.0},{"Year":2017,"Value":2.8},{"Year":2018,"Value":2.7}]}